[
    
    {   
        "model": "stock.SourceInfo",
        "pk": 1,
        "fields": {
          "name": "govcapital",
          "rating": 70
        }
      },
      {
          "model": "stock.SourceInfo",
          "pk": 2,
          "fields": {
            "name": "leoprophet",
            "rating": 80
          }
      },
    {
        "model": "stock.StockInfo",
        "pk": 1,
        "fields": {
          "name": "Virgin Galactic",
          "ticket": "spce",
          "source_id": 1
        }
      },
      {
          "model": "stock.StockInfo",
          "pk": 2,
          "fields": {
            "name": "Virgin Galactic",
            "ticket": "spce",
            "source_id": 2
          }
      },
    {   
        "model": "stock.StockByDate",
        "pk": 0,
        "fields": {
            "ticket_id": 1,
            "min_price": 12.9183,
            "avg_price": 15.198,
            "max_price": 17.4777,
            "forecast_date": "2022-03-01",
            "created_at": "2022-03-01",
            "updated_at": "2022-03-01",
            "outdated_status": false,
            "final_accuracy": 0
        }
    },
    {
        "model": "stock.StockByDate",
        "pk": 1,
        "fields": {
            "ticket_id": 1,
            "min_price": 13.0577,
            "avg_price": 15.362,
            "max_price": 17.6663,
            "forecast_date": "2022-03-02",
            "created_at": "2022-03-01",
            "updated_at": "2022-03-01",
            "outdated_status": false,
            "final_accuracy": 0
        }
    },{
        "model": "stock.StockByDate",
        "pk": 2,
        "fields": {
            "ticket_id": 1,
            "min_price": 12.90555,
            "avg_price": 15.183,
            "max_price": 17.46045,
            "forecast_date": "2022-03-03",
            "created_at": "2022-03-01",
            "updated_at": "2022-03-01",
            "outdated_status": false,
            "final_accuracy": 0
        }
    },{
        "model": "stock.StockByDate",
        "pk": 3,
        "fields": {
            "ticket_id": 1,
            "min_price": 12.903,
            "avg_price": 15.18,
            "max_price": 17.457,
            "forecast_date": "2022-03-04",
            "created_at": "2022-03-01",
            "updated_at": "2022-03-01",
            "outdated_status": false,
            "final_accuracy": 0
        }
    },{
        "model": "stock.StockByDate",
        "pk": 4,
        "fields": {
            "ticket_id": 1,
            "min_price": 12.62845,
            "avg_price": 14.857,
            "max_price": 17.08555,
            "forecast_date": "2022-03-05",
            "created_at": "2022-03-01",
            "updated_at": "2022-03-01",
            "outdated_status": false,
            "final_accuracy": 0
        }
    },{
        "model": "stock.StockByDate",
        "pk": 5,
        "fields": {
            "ticket_id": 1,
            "min_price": 12.7551,
            "avg_price": 15.006,
            "max_price": 17.2569,
            "forecast_date": "2022-03-06",
            "created_at": "2022-03-01",
            "updated_at": "2022-03-01",
            "outdated_status": false,
            "final_accuracy": 0
        }
    },{
        "model": "stock.StockByDate",
        "pk": 6,
        "fields": {
            "ticket_id": 1,
            "min_price": 12.72535,
            "avg_price": 14.971,
            "max_price": 17.21665,
            "forecast_date": "2022-03-07",
            "created_at": "2022-03-01",
            "updated_at": "2022-03-01",
            "outdated_status": false,
            "final_accuracy": 0
        }
    },{
        "model": "stock.StockByDate",
        "pk": 7,
        "fields": {
            "ticket_id": 1,
            "min_price": 12.66755,
            "avg_price": 14.903,
            "max_price": 17.13845,
            "forecast_date": "2022-03-08",
            "created_at": "2022-03-01",
            "updated_at": "2022-03-01",
            "outdated_status": false,
            "final_accuracy": 0
        }
    },{
        "model": "stock.StockByDate",
        "pk": 8,
        "fields": {
            "ticket_id": 1,
            "min_price": 12.20005,
            "avg_price": 14.353,
            "max_price": 16.50595,
            "forecast_date": "2022-03-09",
            "created_at": "2022-03-01",
            "updated_at": "2022-03-01",
            "outdated_status": false,
            "final_accuracy": 0
        }
    },{
        "model": "stock.StockByDate",
        "pk": 9,
        "fields": {
            "ticket_id": 1,
            "min_price": 12.3471,
            "avg_price": 14.526,
            "max_price": 16.7049,
            "forecast_date": "2022-03-10",
            "created_at": "2022-03-01",
            "updated_at": "2022-03-01",
            "outdated_status": false,
            "final_accuracy": 0
        }
    },{
        "model": "stock.StockByDate",
        "pk": 10,
        "fields": {
            "ticket_id": 1,
            "min_price": 12.3709,
            "avg_price": 14.554,
            "max_price": 16.7371,
            "forecast_date": "2022-03-11",
            "created_at": "2022-03-01",
            "updated_at": "2022-03-01",
            "outdated_status": false,
            "final_accuracy": 0
        }
    },{
        "model": "stock.StockByDate",
        "pk": 11,
        "fields": {
            "ticket_id": 1,
            "min_price": 12.02325,
            "avg_price": 14.145,
            "max_price": 16.26675,
            "forecast_date": "2022-03-12",
            "created_at": "2022-03-01",
            "updated_at": "2022-03-01",
            "outdated_status": false,
            "final_accuracy": 0
        }
    },{
        "model": "stock.StockByDate",
        "pk": 12,
        "fields": {
            "ticket_id": 1,
            "min_price": 12.0326,
            "avg_price": 14.156,
            "max_price": 16.2794,
            "forecast_date": "2022-03-13",
            "created_at": "2022-03-01",
            "updated_at": "2022-03-01",
            "outdated_status": false,
            "final_accuracy": 0
        }
    },{
        "model": "stock.StockByDate",
        "pk": 13,
        "fields": {
            "ticket_id": 1,
            "min_price": 11.87025,
            "avg_price": 13.965,
            "max_price": 16.05975,
            "forecast_date": "2022-03-14",
            "created_at": "2022-03-01",
            "updated_at": "2022-03-01",
            "outdated_status": false,
            "final_accuracy": 0
        }
    },{
        "model": "stock.StockByDate",
        "pk": 14,
        "fields": {
            "ticket_id": 1,
            "min_price": 11.5906,
            "avg_price": 13.636,
            "max_price": 15.6814,
            "forecast_date": "2022-03-15",
            "created_at": "2022-03-01",
            "updated_at": "2022-03-01",
            "outdated_status": false,
            "final_accuracy": 0
        }
    },{
        "model": "stock.StockByDate",
        "pk": 15,
        "fields": {
            "ticket_id": 1,
            "min_price": 11.6654,
            "avg_price": 13.724,
            "max_price": 15.7826,
            "forecast_date": "2022-03-16",
            "created_at": "2022-03-01",
            "updated_at": "2022-03-01",
            "outdated_status": false,
            "final_accuracy": 0
        }
    },{
        "model": "stock.StockByDate",
        "pk": 16,
        "fields": {
            "ticket_id": 1,
            "min_price": 11.35515,
            "avg_price": 13.359,
            "max_price": 15.36285,
            "forecast_date": "2022-03-17",
            "created_at": "2022-03-01",
            "updated_at": "2022-03-01",
            "outdated_status": false,
            "final_accuracy": 0
        }
    },{
        "model": "stock.StockByDate",
        "pk": 17,
        "fields": {
            "ticket_id": 1,
            "min_price": 11.3509,
            "avg_price": 13.354,
            "max_price": 15.3571,
            "forecast_date": "2022-03-18",
            "created_at": "2022-03-01",
            "updated_at": "2022-03-01",
            "outdated_status": false,
            "final_accuracy": 0
        }
    },{
        "model": "stock.StockByDate",
        "pk": 18,
        "fields": {
            "ticket_id": 1,
            "min_price": 11.4563,
            "avg_price": 13.478,
            "max_price": 15.4997,
            "forecast_date": "2022-03-19",
            "created_at": "2022-03-01",
            "updated_at": "2022-03-01",
            "outdated_status": false,
            "final_accuracy": 0
        }
    },{
        "model": "stock.StockByDate",
        "pk": 19,
        "fields": {
            "ticket_id": 1,
            "min_price": 11.13075,
            "avg_price": 13.095,
            "max_price": 15.05925,
            "forecast_date": "2022-03-20",
            "created_at": "2022-03-01",
            "updated_at": "2022-03-01",
            "outdated_status": false,
            "final_accuracy": 0
        }
    },{
        "model": "stock.StockByDate",
        "pk": 20,
        "fields": {
            "ticket_id": 1,
            "min_price": 11.01345,
            "avg_price": 12.957,
            "max_price": 14.90055,
            "forecast_date": "2022-03-21",
            "created_at": "2022-03-01",
            "updated_at": "2022-03-01",
            "outdated_status": false,
            "final_accuracy": 0
        }
    },{
        "model": "stock.StockByDate",
        "pk": 21,
        "fields": {
            "ticket_id": 1,
            "min_price": 10.9463,
            "avg_price": 12.878,
            "max_price": 14.8097,
            "forecast_date": "2022-03-22",
            "created_at": "2022-03-01",
            "updated_at": "2022-03-01",
            "outdated_status": false,
            "final_accuracy": 0
        }
    },{
        "model": "stock.StockByDate",
        "pk": 22,
        "fields": {
            "ticket_id": 1,
            "min_price": 10.97775,
            "avg_price": 12.915,
            "max_price": 14.85225,
            "forecast_date": "2022-03-23",
            "created_at": "2022-03-01",
            "updated_at": "2022-03-01",
            "outdated_status": false,
            "final_accuracy": 0
        }
    },{
        "model": "stock.StockByDate",
        "pk": 23,
        "fields": {
            "ticket_id": 1,
            "min_price": 10.83155,
            "avg_price": 12.743,
            "max_price": 14.65445,
            "forecast_date": "2022-03-24",
            "created_at": "2022-03-01",
            "updated_at": "2022-03-01",
            "outdated_status": false,
            "final_accuracy": 0
        }
    },{
        "model": "stock.StockByDate",
        "pk": 24,
        "fields": {
            "ticket_id": 1,
            "min_price": 10.88935,
            "avg_price": 12.811,
            "max_price": 14.73265,
            "forecast_date": "2022-03-25",
            "created_at": "2022-03-01",
            "updated_at": "2022-03-01",
            "outdated_status": false,
            "final_accuracy": 0
        }
    },{
        "model": "stock.StockByDate",
        "pk": 25,
        "fields": {
            "ticket_id": 1,
            "min_price": 10.931,
            "avg_price": 12.86,
            "max_price": 14.789,
            "forecast_date": "2022-03-26",
            "created_at": "2022-03-01",
            "updated_at": "2022-03-01",
            "outdated_status": false,
            "final_accuracy": 0
        }
    },{
        "model": "stock.StockByDate",
        "pk": 26,
        "fields": {
            "ticket_id": 1,
            "min_price": 10.9174,
            "avg_price": 12.844,
            "max_price": 14.7706,
            "forecast_date": "2022-03-27",
            "created_at": "2022-03-01",
            "updated_at": "2022-03-01",
            "outdated_status": false,
            "final_accuracy": 0
        }
    },{
        "model": "stock.StockByDate",
        "pk": 27,
        "fields": {
            "ticket_id": 1,
            "min_price": 10.9055,
            "avg_price": 12.83,
            "max_price": 14.7545,
            "forecast_date": "2022-03-28",
            "created_at": "2022-03-01",
            "updated_at": "2022-03-01",
            "outdated_status": false,
            "final_accuracy": 0
        }
    },{
        "model": "stock.StockByDate",
        "pk": 28,
        "fields": {
            "ticket_id": 1,
            "min_price": 10.9701,
            "avg_price": 12.906,
            "max_price": 14.8419,
            "forecast_date": "2022-03-29",
            "created_at": "2022-03-01",
            "updated_at": "2022-03-01",
            "outdated_status": false,
            "final_accuracy": 0
        }
    },{
        "model": "stock.StockByDate",
        "pk": 29,
        "fields": {
            "ticket_id": 1,
            "min_price": 10.9684,
            "avg_price": 12.904,
            "max_price": 14.8396,
            "forecast_date": "2022-03-30",
            "created_at": "2022-03-01",
            "updated_at": "2022-03-01",
            "outdated_status": false,
            "final_accuracy": 0
        }
    },{
        "model": "stock.StockByDate",
        "pk": 30,
        "fields": {
            "ticket_id": 1,
            "min_price": 10.83495,
            "avg_price": 12.747,
            "max_price": 14.65905,
            "forecast_date": "2022-03-31",
            "created_at": "2022-03-01",
            "updated_at": "2022-03-01",
            "outdated_status": false,
            "final_accuracy": 0
        }
    },{
        "model": "stock.StockByDate",
        "pk": 31,
        "fields": {
            "ticket_id": 1,
            "min_price": 10.95395,
            "avg_price": 12.887,
            "max_price": 14.82005,
            "forecast_date": "2022-04-01",
            "created_at": "2022-03-01",
            "updated_at": "2022-03-01",
            "outdated_status": false,
            "final_accuracy": 0
        }
    },{
        "model": "stock.StockByDate",
        "pk": 32,
        "fields": {
            "ticket_id": 1,
            "min_price": 10.6301,
            "avg_price": 12.506,
            "max_price": 14.3819,
            "forecast_date": "2022-04-02",
            "created_at": "2022-03-01",
            "updated_at": "2022-03-01",
            "outdated_status": false,
            "final_accuracy": 0
        }
    },{
        "model": "stock.StockByDate",
        "pk": 33,
        "fields": {
            "ticket_id": 1,
            "min_price": 10.59185,
            "avg_price": 12.461,
            "max_price": 14.33015,
            "forecast_date": "2022-04-03",
            "created_at": "2022-03-01",
            "updated_at": "2022-03-01",
            "outdated_status": false,
            "final_accuracy": 0
        }
    },{
        "model": "stock.StockByDate",
        "pk": 34,
        "fields": {
            "ticket_id": 1,
            "min_price": 10.54255,
            "avg_price": 12.403,
            "max_price": 14.26345,
            "forecast_date": "2022-04-04",
            "created_at": "2022-03-01",
            "updated_at": "2022-03-01",
            "outdated_status": false,
            "final_accuracy": 0
        }
    },{
        "model": "stock.StockByDate",
        "pk": 35,
        "fields": {
            "ticket_id": 1,
            "min_price": 10.574,
            "avg_price": 12.44,
            "max_price": 14.306,
            "forecast_date": "2022-04-05",
            "created_at": "2022-03-01",
            "updated_at": "2022-03-01",
            "outdated_status": false,
            "final_accuracy": 0
        }
    },{
        "model": "stock.StockByDate",
        "pk": 36,
        "fields": {
            "ticket_id": 1,
            "min_price": 11.7045,
            "avg_price": 13.77,
            "max_price": 15.8355,
            "forecast_date": "2022-04-06",
            "created_at": "2022-03-01",
            "updated_at": "2022-03-01",
            "outdated_status": false,
            "final_accuracy": 0
        }
    },{
        "model": "stock.StockByDate",
        "pk": 37,
        "fields": {
            "ticket_id": 1,
            "min_price": 11.1316,
            "avg_price": 13.096,
            "max_price": 15.0604,
            "forecast_date": "2022-04-07",
            "created_at": "2022-03-01",
            "updated_at": "2022-03-01",
            "outdated_status": false,
            "final_accuracy": 0
        }
    },{
        "model": "stock.StockByDate",
        "pk": 38,
        "fields": {
            "ticket_id": 1,
            "min_price": 11.22765,
            "avg_price": 13.209,
            "max_price": 15.19035,
            "forecast_date": "2022-04-08",
            "created_at": "2022-03-01",
            "updated_at": "2022-03-01",
            "outdated_status": false,
            "final_accuracy": 0
        }
    },{
        "model": "stock.StockByDate",
        "pk": 39,
        "fields": {
            "ticket_id": 1,
            "min_price": 11.22765,
            "avg_price": 13.209,
            "max_price": 15.19035,
            "forecast_date": "2022-04-09",
            "created_at": "2022-03-01",
            "updated_at": "2022-03-01",
            "outdated_status": false,
            "final_accuracy": 0
        }
    },{
        "model": "stock.StockByDate",
        "pk": 40,
        "fields": {
            "ticket_id": 1,
            "min_price": 11.2421,
            "avg_price": 13.226,
            "max_price": 15.2099,
            "forecast_date": "2022-04-10",
            "created_at": "2022-03-01",
            "updated_at": "2022-03-01",
            "outdated_status": false,
            "final_accuracy": 0
        }
    },{
        "model": "stock.StockByDate",
        "pk": 41,
        "fields": {
            "ticket_id": 1,
            "min_price": 11.1928,
            "avg_price": 13.168,
            "max_price": 15.1432,
            "forecast_date": "2022-04-11",
            "created_at": "2022-03-01",
            "updated_at": "2022-03-01",
            "outdated_status": false,
            "final_accuracy": 0
        }
    },{
        "model": "stock.StockByDate",
        "pk": 42,
        "fields": {
            "ticket_id": 1,
            "min_price": 11.30075,
            "avg_price": 13.295,
            "max_price": 15.28925,
            "forecast_date": "2022-04-12",
            "created_at": "2022-03-01",
            "updated_at": "2022-03-01",
            "outdated_status": false,
            "final_accuracy": 0
        }
    },{
        "model": "stock.StockByDate",
        "pk": 43,
        "fields": {
            "ticket_id": 1,
            "min_price": 11.2625,
            "avg_price": 13.25,
            "max_price": 15.2375,
            "forecast_date": "2022-04-13",
            "created_at": "2022-03-01",
            "updated_at": "2022-03-01",
            "outdated_status": false,
            "final_accuracy": 0
        }
    },{
        "model": "stock.StockByDate",
        "pk": 44,
        "fields": {
            "ticket_id": 1,
            "min_price": 10.9378,
            "avg_price": 12.868,
            "max_price": 14.7982,
            "forecast_date": "2022-04-14",
            "created_at": "2022-03-01",
            "updated_at": "2022-03-01",
            "outdated_status": false,
            "final_accuracy": 0
        }
    },{
        "model": "stock.StockByDate",
        "pk": 45,
        "fields": {
            "ticket_id": 1,
            "min_price": 10.87405,
            "avg_price": 12.793,
            "max_price": 14.71195,
            "forecast_date": "2022-04-15",
            "created_at": "2022-03-01",
            "updated_at": "2022-03-01",
            "outdated_status": false,
            "final_accuracy": 0
        }
    },{
        "model": "stock.StockByDate",
        "pk": 46,
        "fields": {
            "ticket_id": 1,
            "min_price": 10.812,
            "avg_price": 12.72,
            "max_price": 14.628,
            "forecast_date": "2022-04-16",
            "created_at": "2022-03-01",
            "updated_at": "2022-03-01",
            "outdated_status": false,
            "final_accuracy": 0
        }
    },{
        "model": "stock.StockByDate",
        "pk": 47,
        "fields": {
            "ticket_id": 1,
            "min_price": 10.897,
            "avg_price": 12.82,
            "max_price": 14.743,
            "forecast_date": "2022-04-17",
            "created_at": "2022-03-01",
            "updated_at": "2022-03-01",
            "outdated_status": false,
            "final_accuracy": 0
        }
    },{
        "model": "stock.StockByDate",
        "pk": 48,
        "fields": {
            "ticket_id": 1,
            "min_price": 10.8477,
            "avg_price": 12.762,
            "max_price": 14.6763,
            "forecast_date": "2022-04-18",
            "created_at": "2022-03-01",
            "updated_at": "2022-03-01",
            "outdated_status": false,
            "final_accuracy": 0
        }
    },{
        "model": "stock.StockByDate",
        "pk": 49,
        "fields": {
            "ticket_id": 1,
            "min_price": 10.99135,
            "avg_price": 12.931,
            "max_price": 14.87065,
            "forecast_date": "2022-04-19",
            "created_at": "2022-03-01",
            "updated_at": "2022-03-01",
            "outdated_status": false,
            "final_accuracy": 0
        }
    },{
        "model": "stock.StockByDate",
        "pk": 50,
        "fields": {
            "ticket_id": 1,
            "min_price": 11.12735,
            "avg_price": 13.091,
            "max_price": 15.05465,
            "forecast_date": "2022-04-20",
            "created_at": "2022-03-01",
            "updated_at": "2022-03-01",
            "outdated_status": false,
            "final_accuracy": 0
        }
    },{
        "model": "stock.StockByDate",
        "pk": 150,
        "fields": {
            "ticket_id": 2,
            "min_price": 6,
            "avg_price": 6.8,
            "max_price": 8.08,
            "forecast_date": "2022-04-20",
            "created_at": "2022-03-01",
            "updated_at": "2022-03-01",
            "outdated_status": false,
            "final_accuracy": 0
        }
    },{
        "model": "stock.StockByDate",
        "pk": 151,
        "fields": {
            "ticket_id": 2,
            "min_price": 7,
            "avg_price": 6.8,
            "max_price": 8.08,
            "forecast_date": "2022-04-21",
            "created_at": "2022-03-01",
            "updated_at": "2022-03-01",
            "outdated_status": false,
            "final_accuracy": 0
        }
    },{
        "model": "stock.StockByDate",
        "pk": 152,
        "fields": {
            "ticket_id": 2,
            "min_price": 7,
            "avg_price": 6.8,
            "max_price": 8.08,
            "forecast_date": "2022-04-22",
            "created_at": "2022-03-01",
            "updated_at": "2022-03-01",
            "outdated_status": false,
            "final_accuracy": 0
        }
    },{
        "model": "stock.StockByDate",
        "pk": 153,
        "fields": {
            "ticket_id": 2,
            "min_price": 6,
            "avg_price": 6.8,
            "max_price": 8.08,
            "forecast_date": "2022-04-23",
            "created_at": "2022-03-01",
            "updated_at": "2022-03-01",
            "outdated_status": false,
            "final_accuracy": 0
        }
    },{
        "model": "stock.StockByDate",
        "pk": 154,
        "fields": {
            "ticket_id": 2,
            "min_price": 7,
            "avg_price": 6.8,
            "max_price": 8.08,
            "forecast_date": "2022-04-24",
            "created_at": "2022-03-01",
            "updated_at": "2022-03-01",
            "outdated_status": false,
            "final_accuracy": 0
        }
    },{
        "model": "stock.StockByDate",
        "pk": 155,
        "fields": {
            "ticket_id": 2,
            "min_price": 7,
            "avg_price": 6.8,
            "max_price": 8.08,
            "forecast_date": "2022-04-25",
            "created_at": "2022-03-01",
            "updated_at": "2022-03-01",
            "outdated_status": false,
            "final_accuracy": 0
        }
    },{
        "model": "stock.StockByDate",
        "pk": 156,
        "fields": {
            "ticket_id": 2,
            "min_price": 7,
            "avg_price": 6.8,
            "max_price": 8.08,
            "forecast_date": "2022-04-26",
            "created_at": "2022-03-01",
            "updated_at": "2022-03-01",
            "outdated_status": false,
            "final_accuracy": 0
        }
    },{
        "model": "stock.StockByDate",
        "pk": 157,
        "fields": {
            "ticket_id": 2,
            "min_price": 7,
            "avg_price": 6.8,
            "max_price": 8.08,
            "forecast_date": "2022-04-27",
            "created_at": "2022-03-01",
            "updated_at": "2022-03-01",
            "outdated_status": false,
            "final_accuracy": 0
        }
    },{
        "model": "stock.StockByDate",
        "pk": 158,
        "fields": {
            "ticket_id": 2,
            "min_price": 7,
            "avg_price": 6.8,
            "max_price": 8.08,
            "forecast_date": "2022-04-28",
            "created_at": "2022-03-01",
            "updated_at": "2022-03-01",
            "outdated_status": false,
            "final_accuracy": 0
        }
    },{
        "model": "stock.StockByDate",
        "pk": 159,
        "fields": {
            "ticket_id": 2,
            "min_price": 7,
            "avg_price": 6.8,
            "max_price": 8.08,
            "forecast_date": "2022-04-29",
            "created_at": "2022-03-01",
            "updated_at": "2022-03-01",
            "outdated_status": false,
            "final_accuracy": 0
        }
    },{
        "model": "stock.StockByDate",
        "pk": 160,
        "fields": {
            "ticket_id": 2,
            "min_price": 7,
            "avg_price": 6.8,
            "max_price": 8.08,
            "forecast_date": "2022-04-30",
            "created_at": "2022-03-01",
            "updated_at": "2022-03-01",
            "outdated_status": false,
            "final_accuracy": 0
        }
    },{
        "model": "stock.StockByDate",
        "pk": 161,
        "fields": {
            "ticket_id": 2,
            "min_price": 6,
            "avg_price": 6.52,
            "max_price": 7.59,
            "forecast_date": "2022-05-01",
            "created_at": "2022-03-01",
            "updated_at": "2022-03-01",
            "outdated_status": false,
            "final_accuracy": 0
        }
    },{
        "model": "stock.StockByDate",
        "pk": 162,
        "fields": {
            "ticket_id": 2,
            "min_price": 6,
            "avg_price": 7,
            "max_price": 7.59,
            "forecast_date": "2022-05-02",
            "created_at": "2022-03-01",
            "updated_at": "2022-03-01",
            "outdated_status": false,
            "final_accuracy": 0
        }
    },{
        "model": "stock.StockByDate",
        "pk": 163,
        "fields": {
            "ticket_id": 2,
            "min_price": 6,
            "avg_price": 6.52,
            "max_price": 7.59,
            "forecast_date": "2022-05-03",
            "created_at": "2022-03-01",
            "updated_at": "2022-03-01",
            "outdated_status": false,
            "final_accuracy": 0
        }
    },{
        "model": "stock.StockByDate",
        "pk": 164,
        "fields": {
            "ticket_id": 2,
            "min_price": 6,
            "avg_price": 6.52,
            "max_price": 7.59,
            "forecast_date": "2022-05-04",
            "created_at": "2022-03-01",
            "updated_at": "2022-03-01",
            "outdated_status": false,
            "final_accuracy": 0
        }
    },{
        "model": "stock.StockByDate",
        "pk": 165,
        "fields": {
            "ticket_id": 2,
            "min_price": 6,
            "avg_price": 6.52,
            "max_price": 7.59,
            "forecast_date": "2022-05-05",
            "created_at": "2022-03-01",
            "updated_at": "2022-03-01",
            "outdated_status": false,
            "final_accuracy": 0
        }
    },{
        "model": "stock.StockByDate",
        "pk": 166,
        "fields": {
            "ticket_id": 2,
            "min_price": 6,
            "avg_price": 6.52,
            "max_price": 7.59,
            "forecast_date": "2022-05-06",
            "created_at": "2022-03-01",
            "updated_at": "2022-03-01",
            "outdated_status": false,
            "final_accuracy": 0
        }
    },{
        "model": "stock.StockByDate",
        "pk": 167,
        "fields": {
            "ticket_id": 2,
            "min_price": 6,
            "avg_price": 6.52,
            "max_price": 7.59,
            "forecast_date": "2022-05-07",
            "created_at": "2022-03-01",
            "updated_at": "2022-03-01",
            "outdated_status": false,
            "final_accuracy": 0
        }
    },{
        "model": "stock.StockByDate",
        "pk": 168,
        "fields": {
            "ticket_id": 2,
            "min_price": 6,
            "avg_price": 6.52,
            "max_price": 7.59,
            "forecast_date": "2022-05-08",
            "created_at": "2022-03-01",
            "updated_at": "2022-03-01",
            "outdated_status": false,
            "final_accuracy": 0
        }
    },{
        "model": "stock.StockByDate",
        "pk": 169,
        "fields": {
            "ticket_id": 2,
            "min_price": 6,
            "avg_price": 6.52,
            "max_price": 7.59,
            "forecast_date": "2022-05-09",
            "created_at": "2022-03-01",
            "updated_at": "2022-03-01",
            "outdated_status": false,
            "final_accuracy": 0
        }
    },{
        "model": "stock.StockByDate",
        "pk": 170,
        "fields": {
            "ticket_id": 2,
            "min_price": 6,
            "avg_price": 6.52,
            "max_price": 7.59,
            "forecast_date": "2022-05-10",
            "created_at": "2022-03-01",
            "updated_at": "2022-03-01",
            "outdated_status": false,
            "final_accuracy": 0
        }
    },{
        "model": "stock.StockByDate",
        "pk": 171,
        "fields": {
            "ticket_id": 2,
            "min_price": 6,
            "avg_price": 6.52,
            "max_price": 7.59,
            "forecast_date": "2022-05-11",
            "created_at": "2022-03-01",
            "updated_at": "2022-03-01",
            "outdated_status": false,
            "final_accuracy": 0
        }
    },{
        "model": "stock.StockByDate",
        "pk": 172,
        "fields": {
            "ticket_id": 2,
            "min_price": 6,
            "avg_price": 6.52,
            "max_price": 7.59,
            "forecast_date": "2022-05-12",
            "created_at": "2022-03-01",
            "updated_at": "2022-03-01",
            "outdated_status": false,
            "final_accuracy": 0
        }
    },{
        "model": "stock.StockByDate",
        "pk": 173,
        "fields": {
            "ticket_id": 2,
            "min_price": 6,
            "avg_price": 6.52,
            "max_price": 7.59,
            "forecast_date": "2022-05-13",
            "created_at": "2022-03-01",
            "updated_at": "2022-03-01",
            "outdated_status": false,
            "final_accuracy": 0
        }
    },{
        "model": "stock.StockByDate",
        "pk": 174,
        "fields": {
            "ticket_id": 2,
            "min_price": 6,
            "avg_price": 6.52,
            "max_price": 7.59,
            "forecast_date": "2022-05-14",
            "created_at": "2022-03-01",
            "updated_at": "2022-03-01",
            "outdated_status": false,
            "final_accuracy": 0
        }
    },{
        "model": "stock.StockByDate",
        "pk": 175,
        "fields": {
            "ticket_id": 2,
            "min_price": 6,
            "avg_price": 6.52,
            "max_price": 7.59,
            "forecast_date": "2022-05-15",
            "created_at": "2022-03-01",
            "updated_at": "2022-03-01",
            "outdated_status": false,
            "final_accuracy": 0
        }
    },{
        "model": "stock.StockByDate",
        "pk": 176,
        "fields": {
            "ticket_id": 2,
            "min_price": 6,
            "avg_price": 7,
            "max_price": 7.59,
            "forecast_date": "2022-05-16",
            "created_at": "2022-03-01",
            "updated_at": "2022-03-01",
            "outdated_status": false,
            "final_accuracy": 0
        }
    },{
        "model": "stock.StockByDate",
        "pk": 177,
        "fields": {
            "ticket_id": 2,
            "min_price": 6,
            "avg_price": 6.52,
            "max_price": 7.59,
            "forecast_date": "2022-05-17",
            "created_at": "2022-03-01",
            "updated_at": "2022-03-01",
            "outdated_status": false,
            "final_accuracy": 0
        }
    },{
        "model": "stock.StockByDate",
        "pk": 178,
        "fields": {
            "ticket_id": 2,
            "min_price": 6,
            "avg_price": 6.52,
            "max_price": 7.59,
            "forecast_date": "2022-05-18",
            "created_at": "2022-03-01",
            "updated_at": "2022-03-01",
            "outdated_status": false,
            "final_accuracy": 0
        }
    },{
        "model": "stock.StockByDate",
        "pk": 179,
        "fields": {
            "ticket_id": 2,
            "min_price": 6,
            "avg_price": 6.52,
            "max_price": 7.59,
            "forecast_date": "2022-05-19",
            "created_at": "2022-03-01",
            "updated_at": "2022-03-01",
            "outdated_status": false,
            "final_accuracy": 0
        }
    },{
        "model": "stock.StockByDate",
        "pk": 180,
        "fields": {
            "ticket_id": 2,
            "min_price": 6,
            "avg_price": 6.52,
            "max_price": 7.59,
            "forecast_date": "2022-05-20",
            "created_at": "2022-03-01",
            "updated_at": "2022-03-01",
            "outdated_status": false,
            "final_accuracy": 0
        }
    },{
        "model": "stock.StockByDate",
        "pk": 181,
        "fields": {
            "ticket_id": 2,
            "min_price": 6,
            "avg_price": 6.52,
            "max_price": 7.59,
            "forecast_date": "2022-05-21",
            "created_at": "2022-03-01",
            "updated_at": "2022-03-01",
            "outdated_status": false,
            "final_accuracy": 0
        }
    },{
        "model": "stock.StockByDate",
        "pk": 182,
        "fields": {
            "ticket_id": 2,
            "min_price": 6,
            "avg_price": 6.5,
            "max_price": 7.59,
            "forecast_date": "2022-05-22",
            "created_at": "2022-03-01",
            "updated_at": "2022-03-01",
            "outdated_status": false,
            "final_accuracy": 0
        }
    },{
        "model": "stock.StockByDate",
        "pk": 183,
        "fields": {
            "ticket_id": 2,
            "min_price": 6,
            "avg_price": 6.52,
            "max_price": 7.59,
            "forecast_date": "2022-05-23",
            "created_at": "2022-03-01",
            "updated_at": "2022-03-01",
            "outdated_status": false,
            "final_accuracy": 0
        }
    },{
        "model": "stock.StockByDate",
        "pk": 184,
        "fields": {
            "ticket_id": 2,
            "min_price": 6,
            "avg_price": 6.52,
            "max_price": 7.59,
            "forecast_date": "2022-05-24",
            "created_at": "2022-03-01",
            "updated_at": "2022-03-01",
            "outdated_status": false,
            "final_accuracy": 0
        }
    },{
        "model": "stock.StockByDate",
        "pk": 185,
        "fields": {
            "ticket_id": 2,
            "min_price": 6,
            "avg_price": 6.52,
            "max_price": 7.59,
            "forecast_date": "2022-05-25",
            "created_at": "2022-03-01",
            "updated_at": "2022-03-01",
            "outdated_status": false,
            "final_accuracy": 0
        }
    },{
        "model": "stock.StockByDate",
        "pk": 186,
        "fields": {
            "ticket_id": 2,
            "min_price": 6,
            "avg_price": 6.52,
            "max_price": 7.59,
            "forecast_date": "2022-05-26",
            "created_at": "2022-03-01",
            "updated_at": "2022-03-01",
            "outdated_status": false,
            "final_accuracy": 0
        }
    },{
        "model": "stock.StockByDate",
        "pk": 187,
        "fields": {
            "ticket_id": 2,
            "min_price": 6,
            "avg_price": 6.52,
            "max_price": 7.59,
            "forecast_date": "2022-05-27",
            "created_at": "2022-03-01",
            "updated_at": "2022-03-01",
            "outdated_status": false,
            "final_accuracy": 0
        }
    },{
        "model": "stock.StockByDate",
        "pk": 188,
        "fields": {
            "ticket_id": 2,
            "min_price": 6,
            "avg_price": 6.52,
            "max_price": 7.59,
            "forecast_date": "2022-05-28",
            "created_at": "2022-03-01",
            "updated_at": "2022-03-01",
            "outdated_status": false,
            "final_accuracy": 0
        }
    },{
        "model": "stock.StockByDate",
        "pk": 189,
        "fields": {
            "ticket_id": 2,
            "min_price": 6,
            "avg_price": 6.52,
            "max_price": 7.59,
            "forecast_date": "2022-05-29",
            "created_at": "2022-03-01",
            "updated_at": "2022-03-01",
            "outdated_status": false,
            "final_accuracy": 0
        }
    },{
        "model": "stock.StockByDate",
        "pk": 190,
        "fields": {
            "ticket_id": 2,
            "min_price": 6,
            "avg_price": 6.52,
            "max_price": 7.59,
            "forecast_date": "2022-05-30",
            "created_at": "2022-03-01",
            "updated_at": "2022-03-01",
            "outdated_status": false,
            "final_accuracy": 0
        }
    },{
        "model": "stock.StockByDate",
        "pk": 191,
        "fields": {
            "ticket_id": 2,
            "min_price": 6,
            "avg_price": 6.52,
            "max_price": 7.59,
            "forecast_date": "2022-05-31",
            "created_at": "2022-03-01",
            "updated_at": "2022-03-01",
            "outdated_status": false,
            "final_accuracy": 0
        }
    },{
        "model": "stock.StockByDate",
        "pk": 192,
        "fields": {
            "ticket_id": 2,
            "min_price": 5,
            "avg_price": 5.46,
            "max_price": 6.63,
            "forecast_date": "2022-06-01",
            "created_at": "2022-03-01",
            "updated_at": "2022-03-01",
            "outdated_status": false,
            "final_accuracy": 0
        }
    },{
        "model": "stock.StockByDate",
        "pk": 193,
        "fields": {
            "ticket_id": 2,
            "min_price": 5,
            "avg_price": 5.46,
            "max_price": 6.63,
            "forecast_date": "2022-06-02",
            "created_at": "2022-03-01",
            "updated_at": "2022-03-01",
            "outdated_status": false,
            "final_accuracy": 0
        }
    },{
        "model": "stock.StockByDate",
        "pk": 194,
        "fields": {
            "ticket_id": 2,
            "min_price": 5,
            "avg_price": 5.46,
            "max_price": 6.63,
            "forecast_date": "2022-06-03",
            "created_at": "2022-03-01",
            "updated_at": "2022-03-01",
            "outdated_status": false,
            "final_accuracy": 0
        }
    },{
        "model": "stock.StockByDate",
        "pk": 195,
        "fields": {
            "ticket_id": 2,
            "min_price": 5,
            "avg_price": 5.46,
            "max_price": 6.63,
            "forecast_date": "2022-06-04",
            "created_at": "2022-03-01",
            "updated_at": "2022-03-01",
            "outdated_status": false,
            "final_accuracy": 0
        }
    },{
        "model": "stock.StockByDate",
        "pk": 196,
        "fields": {
            "ticket_id": 2,
            "min_price": 5,
            "avg_price": 5.46,
            "max_price": 6.63,
            "forecast_date": "2022-06-05",
            "created_at": "2022-03-01",
            "updated_at": "2022-03-01",
            "outdated_status": false,
            "final_accuracy": 0
        }
    },{
        "model": "stock.StockByDate",
        "pk": 197,
        "fields": {
            "ticket_id": 2,
            "min_price": 5,
            "avg_price": 5.46,
            "max_price": 6.63,
            "forecast_date": "2022-06-06",
            "created_at": "2022-03-01",
            "updated_at": "2022-03-01",
            "outdated_status": false,
            "final_accuracy": 0
        }
    },{
        "model": "stock.StockByDate",
        "pk": 198,
        "fields": {
            "ticket_id": 2,
            "min_price": 5,
            "avg_price": 5.46,
            "max_price": 6.63,
            "forecast_date": "2022-06-07",
            "created_at": "2022-03-01",
            "updated_at": "2022-03-01",
            "outdated_status": false,
            "final_accuracy": 0
        }
    },{
        "model": "stock.StockByDate",
        "pk": 199,
        "fields": {
            "ticket_id": 2,
            "min_price": 5,
            "avg_price": 5.46,
            "max_price": 6.63,
            "forecast_date": "2022-06-08",
            "created_at": "2022-03-01",
            "updated_at": "2022-03-01",
            "outdated_status": false,
            "final_accuracy": 0
        }
    }
]